README.rst
setup.cfg
setup.py
xkcd_dl/__init__.py
xkcd_dl/cli.py
xkcd_dl/version.py
xkcd_dl.egg-info/PKG-INFO
xkcd_dl.egg-info/SOURCES.txt
xkcd_dl.egg-info/dependency_links.txt
xkcd_dl.egg-info/entry_points.txt
xkcd_dl.egg-info/requires.txt
xkcd_dl.egg-info/top_level.txt