Metadata-Version: 1.1
Name: xkcd-dl
Version: 0.1.2
Summary: Download all the XKCD's uploaded, ever from the command line
Home-page: https://github.com/prodicus/xkcd-dl
Author: Tasdik Rahman
Author-email: prodicus@outlook.com
License: MIT
Download-URL: https://github.com/prodicus/xkcd-dl/tarball/0.1.2
Keywords: xkcd,cli,commandline,download,api,comic
Platform: UNKNOWN
Classifier: Intended Audience :: Developers
Classifier: Topic :: Software Development :: Build Tools
Classifier: Environment :: Console
Classifier: Intended Audience :: Developers
Classifier: License :: OSI Approved :: MIT License
Classifier: Natural Language :: English
Classifier: Programming Language :: Python
Classifier: Programming Language :: Python :: 3
Classifier: Programming Language :: Python :: 3.4
